auto_di_tag.py
auto_di_tag-0.2.7.dist-info/licenses/LICENSE
auto_di_tag-0.2.7.dist-info/METADATA
auto_di_tag-0.2.7.dist-info/WHEEL
auto_di_tag-0.2.7.dist-info/entry_points.txt
auto_di_tag-0.2.7.dist-info/top_level.txt
auto_di_tag-0.2.7.dist-info/RECORD
