Metadata-Version: 2.4
Name: auto_di_tag
Version: 0.2.7
Summary: Automatically create rename and tag your dance playlist
Author-email: Klassenserver7b <klassenserver7bwin10@gmail.com>
License-Expression: MIT
Project-URL: Homepage, https://github.com/klassenserver7b/AutoDITag
Project-URL: Issues, https://github.com/klassenserver7b/AutoDITag/issues
Classifier: Programming Language :: Python :: 3
Classifier: Operating System :: OS Independent
Classifier: Environment :: Console
Classifier: Intended Audience :: End Users/Desktop
Classifier: Topic :: Multimedia :: Sound/Audio
Requires-Python: >=3.9
License-File: LICENSE
Requires-Dist: mutagen>=1.45
Requires-Dist: argparse>=1.4
Provides-Extra: dev
Requires-Dist: pytest; extra == "dev"
Requires-Dist: black; extra == "dev"
Requires-Dist: flake8; extra == "dev"
Dynamic: license-file
